{
    "version": 1,
    "all_bricks": {
        "15": {
            "submit_time": [
                1720096426
            ],
            "type": 4,
            "review_day": [
                1720108800,
                1720368000,
                1720627200,
                1721232000,
                1722441600,
                1725206400
            ]
        },
        "18": {
            "submit_time": [
                1720144727,
                1720144737,
                1720144829
            ],
            "type": 4,
            "review_day": [
                1720195200,
                1720454400,
                1720713600,
                1721318400,
                1722528000,
                1725292800
            ]
        },
        "32": {
            "submit_time": [
                1720071053,
                1720072368
            ],
            "type": 4,
            "review_day": [
                1720108800,
                1720368000,
                1720627200,
                1721232000,
                1722441600,
                1725206400
            ]
        },
        "45": {
            "submit_time": [
                1720255732
            ],
            "type": 4,
            "review_day": [
                1720281600,
                1720540800,
                1720800000,
                1721404800,
                1722614400,
                1725379200
            ]
        },
        "51": {
            "submit_time": [
                1720086145
            ],
            "type": 4,
            "review_day": [
                1720108800,
                1720368000,
                1720627200,
                1721232000,
                1722441600,
                1725206400
            ]
        },
        "72": {
            "submit_time": [
                1720149588,
                1720149599
            ],
            "type": 4,
            "review_day": [
                1720195200,
                1720454400,
                1720713600,
                1721318400,
                1722528000,
                1725292800
            ]
        },
        "76": {
            "submit_time": [
                1720254179
            ],
            "type": 4,
            "review_day": [
                1720281600,
                1720540800,
                1720800000,
                1721404800,
                1722614400,
                1725379200
            ]
        },
        "128": {
            "submit_time": [
                1720073237
            ],
            "type": 4,
            "review_day": [
                1720108800,
                1720368000,
                1720627200,
                1721232000,
                1722441600,
                1725206400
            ]
        },
        "300": {
            "submit_time": [
                1720019983
            ],
            "type": 4,
            "review_day": [
                1720022400,
                1720281600,
                1720540800,
                1721145600,
                1722355200,
                1725120000
            ]
        },
        "455": {
            "submit_time": [
                1720090785
            ],
            "type": 4,
            "review_day": [
                1720108800,
                1720368000,
                1720627200,
                1721232000,
                1722441600,
                1725206400
            ]
        },
        "475": {
            "submit_time": [
                1720092876,
                1720093267
            ],
            "type": 4,
            "review_day": [
                1720108800,
                1720368000,
                1720627200,
                1721232000,
                1722441600,
                1725206400
            ]
        },
        "1428": {
            "submit_time": [
                1720258469
            ],
            "type": 4,
            "review_day": [
                1720281600,
                1720540800,
                1720800000,
                1721404800,
                1722614400,
                1725379200
            ]
        },
        "2444": {
            "submit_time": [
                1720018018
            ],
            "type": 4,
            "review_day": [
                1720022400,
                1720281600,
                1720540800,
                1721145600,
                1722355200,
                1725120000
            ]
        },
        "3330": {
            "submit_time": [
                1720145535
            ],
            "type": 4,
            "review_day": [
                1720195200,
                1720454400,
                1720713600,
                1721318400,
                1722528000,
                1725292800
            ]
        },
        "3371": {
            "submit_time": [
                1719998806
            ],
            "type": 4,
            "review_day": [
                1720022400,
                1720281600,
                1720540800,
                1721145600,
                1722355200,
                1725120000
            ]
        },
        "3374": {
            "submit_time": [
                1720247768,
                1720248147
            ],
            "type": 4,
            "review_day": [
                1720281600,
                1720540800,
                1720800000,
                1721404800,
                1722614400,
                1725379200
            ]
        },
        "100158": {
            "submit_time": [
                1720094285,
                1720094466,
                1720094752
            ],
            "type": 4,
            "review_day": [
                1720108800,
                1720368000,
                1720627200,
                1721232000,
                1722441600,
                1725206400
            ]
        },
        "100344": {
            "submit_time": [
                1720093990
            ],
            "type": 4,
            "review_day": [
                1720108800,
                1720368000,
                1720627200,
                1721232000,
                1722441600,
                1725206400
            ]
        }
    }
}